{
  "duration": "222000",
  "layout": {
    "children": [
      {
        "bounds": {
          "top": "0",
          "left": "398",
          "bottom": "144",
          "right": "682"
        },
        "id": "button17",
        "class": "MaterialButton"
      },
      {
        "bounds": {
          "top": "0",
          "left": "114",
          "bottom": "144",
          "right": "398"
        },
        "id": "button18",
        "class": "MaterialButton"
      },
      {
        "bounds": {
          "top": "0",
          "left": "682",
          "bottom": "144",
          "right": "966"
        },
        "id": "button19",
        "class": "MaterialButton"
      }
    ],
    "bounds": {
      "top": "0",
      "left": "0",
      "bottom": "144",
      "right": "1080"
    },
    "class": "ConstraintLayout"
  }
}