{
  "duration": "149000",
  "layout": {
    "children": [
      {
        "bounds": {
          "top": "339",
          "left": "24",
          "bottom": "1197",
          "right": "285"
        },
        "id": "button126",
        "class": "MaterialButton"
      },
      {
        "bounds": {
          "top": "590",
          "left": "309",
          "bottom": "647",
          "right": "480"
        },
        "id": "textView23",
        "class": "MaterialTextView"
      },
      {
        "bounds": {
          "top": "647",
          "left": "309",
          "bottom": "947",
          "right": "609"
        },
        "id": "textView24",
        "class": "MaterialTextView"
      }
    ],
    "bounds": {
      "top": "0",
      "left": "0",
      "bottom": "1536",
      "right": "609"
    },
    "class": "ConstraintLayout"
  }
}