{
  "duration": "217000",
  "layout": {
    "children": [
      {
        "children": [],
        "bounds": {
          "top": "0",
          "left": "0",
          "bottom": "1536",
          "right": "540"
        },
        "id": "leftLayout2",
        "class": "FrameLayout"
      },
      {
        "children": [{
          "bounds": {
            "top": "0",
            "left": "0",
            "bottom": "57",
            "right": "540"
          },
          "id": "text2",
          "class": "MaterialTextView"
        }],
        "bounds": {
          "top": "740",
          "left": "540",
          "bottom": "797",
          "right": "1080"
        },
        "id": "rightLayout2",
        "class": "LinearLayout"
      },
      {
        "bounds": {
          "top": "0",
          "left": "0",
          "bottom": "1536",
          "right": "1080"
        },
        "id": "flow2",
        "class": "Flow"
      }
    ],
    "bounds": {
      "top": "0",
      "left": "0",
      "bottom": "1536",
      "right": "1080"
    },
    "class": "ConstraintLayout"
  }
}