{
  "duration": "154476",
  "layout": {
    "children": [{
      "children": [
        {
          "bounds": {
            "top": "17",
            "left": "1032",
            "bottom": "41",
            "right": "1056"
          },
          "id": "serverFavIcon",
          "class": "AppCompatImageView"
        },
        {
          "children": [
            {
              "bounds": {
                "top": "0",
                "left": "1020",
                "bottom": "57",
                "right": "1020"
              },
              "id": "hostSponsor_textView",
              "class": "AppCompatTextView"
            },
            {
              "bounds": {
                "top": "0",
                "left": "984",
                "bottom": "57",
                "right": "1014"
              },
              "id": "caret",
              "class": "AppCompatImageView"
            }
          ],
          "bounds": {
            "top": "0",
            "left": "0",
            "bottom": "57",
            "right": "1032"
          },
          "id": "hostTextWithCaretContainer",
          "class": "ConstraintLayout"
        },
        {
          "bounds": {
            "top": "57",
            "left": "24",
            "bottom": "114",
            "right": "1056"
          },
          "id": "hostname_textView",
          "class": "AppCompatTextView"
        }
      ],
      "bounds": {
        "top": "0",
        "left": "0",
        "bottom": "114",
        "right": "1080"
      },
      "id": "topTextInnerContainer_constraintLayout",
      "class": "ConstraintLayout"
    }],
    "bounds": {
      "top": "0",
      "left": "0",
      "bottom": "114",
      "right": "1080"
    },
    "id": "hostAssembly_constraintLayout",
    "class": "ConstraintLayout"
  }
}