{
  "duration": "132048",
  "layout": {
    "children": [
      {
        "bounds": {
          "top": "480",
          "left": "24",
          "bottom": "624",
          "right": "288"
        },
        "id": "button17",
        "class": "AppCompatButton"
      },
      {
        "bounds": {
          "top": "336",
          "left": "24",
          "bottom": "480",
          "right": "288"
        },
        "id": "button18",
        "class": "AppCompatButton"
      },
      {
        "bounds": {
          "top": "624",
          "left": "48",
          "bottom": "768",
          "right": "312"
        },
        "id": "button19",
        "class": "AppCompatButton"
      },
      {
        "bounds": {
          "top": "792",
          "left": "24",
          "bottom": "936",
          "right": "288"
        },
        "id": "button20",
        "class": "AppCompatButton"
      },
      {
        "bounds": {
          "top": "960",
          "left": "0",
          "bottom": "1104",
          "right": "264"
        },
        "id": "button21",
        "class": "AppCompatButton"
      },
      {
        "bounds": {
          "top": "168",
          "left": "0",
          "bottom": "312",
          "right": "264"
        },
        "id": "button22",
        "class": "AppCompatButton"
      }
    ],
    "bounds": {
      "top": "0",
      "left": "0",
      "bottom": "1104",
      "right": "312"
    },
    "class": "ConstraintLayout"
  }
}